flake8_ejudge/__init__.py
flake8_ejudge/__main__.py
flake8_ejudge/flake8_ejudge_runner.py
flake8_ejudge/flake8_ejudgeformatter.py
flake8_ejudge/flake8_returnyesno.py
flake8_ejudge/flake8_ruerrors.py
flake8_ejudge-0.5.5.dist-info/LICENSE
flake8_ejudge-0.5.5.dist-info/METADATA
flake8_ejudge-0.5.5.dist-info/WHEEL
flake8_ejudge-0.5.5.dist-info/entry_points.txt
flake8_ejudge-0.5.5.dist-info/top_level.txt
flake8_ejudge-0.5.5.dist-info/RECORD
