Metadata-Version: 2.1
Name: flake8-ejudge
Version: 0.5.5
Summary: Проверка стиля и требований к используемому синтаксису в python коде для ejudge
Home-page: https://github.com/ShashkovS/flake8_ejudge
Author: Sergey Shashkov
Author-email: sh57@yandex.ru
License: MIT
Classifier: Development Status :: 4 - Beta
Classifier: Environment :: Console
Classifier: Framework :: Flake8
Classifier: Intended Audience :: Developers
Classifier: Intended Audience :: Education
Classifier: License :: OSI Approved :: MIT License
Classifier: Natural Language :: Russian
Classifier: Operating System :: OS Independent
Classifier: Programming Language :: Python
Classifier: Programming Language :: Python :: 3
Classifier: Programming Language :: Python :: 3.7
Classifier: Programming Language :: Python :: 3.8
Classifier: Programming Language :: Python :: 3.9
Classifier: Programming Language :: Python :: 3.10
Classifier: Programming Language :: Python :: 3.11
Classifier: Programming Language :: Python :: Implementation :: CPython
Classifier: Topic :: Software Development :: Quality Assurance
License-File: LICENSE
Requires-Dist: flake8 (>=5.0.0)
Requires-Dist: flake8-builtins (>=1.5.3)
